lepton/__init__.py
lepton/exceptions.py
lepton/main.py
lepton/comm/__init__.py
lepton/comm/oneway_socket.py
lepton/core/__init__.py
lepton/core/camera.py
lepton/core/detector.py
lepton/core/record.py
lepton/core/_media/overlay.cdat
lepton/misc/__init__.py
lepton/misc/cmaps.py
lepton/misc/utilities.py
lepton_pt-0.3b11.dist-info/licenses/LICENSE.txt
lepton_pt-0.3b11.dist-info/METADATA
lepton_pt-0.3b11.dist-info/WHEEL
lepton_pt-0.3b11.dist-info/entry_points.txt
lepton_pt-0.3b11.dist-info/top_level.txt
lepton_pt-0.3b11.dist-info/RECORD
