Metadata-Version: 2.4
Name: lepton-pt
Version: 0.3b11
Summary: Runs a FLIR Lepton 3.5 on a Purethermal3 in Windows 10.
Author-email: Grayson Schaer <gschaer2@illinois.edu>
Maintainer-email: Grayson Schaer <gschaer2@illinois.edu>
License: Attribution-ShareAlike 4.0 International
Project-URL: Homepage, https://github.com/GrayKS3248/Lepton3.5_Purethermal3/
Project-URL: Bug Reports, https://github.com/GrayKS3248/Lepton3.5_Purethermal3/issues
Project-URL: Source, https://github.com/GrayKS3248/Lepton3.5_Purethermal3/
Keywords: flir,lepton,groupgets,purethermal,windows,thermal,camera
Classifier: Development Status :: 3 - Alpha
Classifier: Intended Audience :: Developers
Classifier: Intended Audience :: End Users/Desktop
Classifier: Intended Audience :: Science/Research
Classifier: Natural Language :: English
Classifier: Operating System :: Microsoft :: Windows :: Windows 10
Classifier: Topic :: Scientific/Engineering :: Image Processing
Classifier: Programming Language :: Python :: 3
Classifier: Programming Language :: Python :: 3.12
Classifier: Programming Language :: Python :: 3.13
Classifier: Programming Language :: Python :: 3 :: Only
Requires-Python: >=3.12
License-File: LICENSE.txt
Requires-Dist: numpy
Requires-Dist: matplotlib
Requires-Dist: scipy
Requires-Dist: opencv-python
Requires-Dist: av
Dynamic: license-file
